scratchcloudclient/CloudConnection.py
scratchcloudclient/CloudUtils.py
scratchcloudclient/ScratchSession.py
scratchcloudclient/__init__.py
scratchcloudclient-0.0.3.dist-info/LICENSE
scratchcloudclient-0.0.3.dist-info/METADATA
scratchcloudclient-0.0.3.dist-info/WHEEL
scratchcloudclient-0.0.3.dist-info/top_level.txt
scratchcloudclient-0.0.3.dist-info/RECORD
