Metadata-Version: 2.1
Name: scratchcloudclient
Version: 0.0.3
Summary: Python client for Scratch Cloud Variables
Home-page: https://github.com/xAspirus/scratchcloudclient
Author: Aspirus
Author-email: movxa@protonmail.com
License: UNKNOWN
Project-URL: Bug Tracker, https://github.com/xAspirus/scratchcloudclient/issues
Platform: UNKNOWN
Classifier: Programming Language :: Python :: 3
Classifier: License :: OSI Approved :: MIT License
Classifier: Operating System :: OS Independent
Requires-Python: >=3.6
License-File: LICENSE
